AlloySustainability/__init__.py
AlloySustainability/computations.py
AlloySustainability/visualization.py
AlloySustainability/data/gen_HTHEAs_vs_Ni_df.csv
AlloySustainability/data/gen_RTHEAs_vs_Fe_df.csv
AlloySustainability-0.1.7.dist-info/METADATA
AlloySustainability-0.1.7.dist-info/WHEEL
AlloySustainability-0.1.7.dist-info/top_level.txt
AlloySustainability-0.1.7.dist-info/RECORD
