Metadata-Version: 2.1
Name: AlloySustainability
Version: 0.1.7
Summary: Compute and visualize the sustainability impacts of alloys based on their chemical composition.
Author-email: Stephane GORSSE <sgorsse@gmail.com>
License: MIT
Project-URL: Homepage, https://github.com/sgorsse/AlloySustainability
Classifier: Programming Language :: Python :: 3
Classifier: License :: OSI Approved :: MIT License
Classifier: Operating System :: OS Independent
Requires-Python: >=3.6
Requires-Dist: numpy
Requires-Dist: pandas
Requires-Dist: matplotlib
Requires-Dist: seaborn
Requires-Dist: requests
